package/__init__.py
package/datadog_utils.py
package/main.py
package/opsgenie_utils.py
tests/__init__.py
tests/test_main.py
datadog_muted_alert_checker-1.0.2.dist-info/LICENSE
datadog_muted_alert_checker-1.0.2.dist-info/METADATA
datadog_muted_alert_checker-1.0.2.dist-info/WHEEL
datadog_muted_alert_checker-1.0.2.dist-info/entry_points.txt
datadog_muted_alert_checker-1.0.2.dist-info/top_level.txt
datadog_muted_alert_checker-1.0.2.dist-info/RECORD
