Metadata-Version: 2.1
Name: datadog-muted-alert-checker
Version: 1.0.2
Summary: UNKNOWN
Home-page: https://github.com/zackzonexx/datadog-muted-alert-checker
Author: Zackzonexx
Author-email: zackzonexx@gmail.com
License: MIT
Keywords: Datadog Muted Alert Checker
Platform: UNKNOWN
Classifier: License :: OSI Approved :: MIT License
Classifier: Programming Language :: Python :: 3
Classifier: Operating System :: OS Independent
Classifier: Development Status :: 3 - Alpha
Classifier: Intended Audience :: Developers
Classifier: Topic :: Software Development :: Libraries :: Python Modules
Classifier: Natural Language :: English
Requires-Dist: datadog
Requires-Dist: google-api-python-client
Requires-Dist: google-auth
Requires-Dist: google-auth-httplib2
Requires-Dist: opsgenie-sdk
Requires-Dist: pytest
Requires-Dist: requests
Requires-Dist: urllib3
